{
  "url": "http://localhost:3000/api-docs",
  "timestamp": "2025-11-25T18:28:29.811Z",
  "duration": 7575,
  "browserType": "chromium",
  "status": "failed",
  "issues": [
    {
      "type": "MISSING_FORM_LABELS",
      "severity": "high",
      "message": "♿ 1 form input(s) missing labels",
      "fix": [
        "Add <label> element for each input",
        "Use for attribute to associate label with input",
        "Use aria-label for inputs without visible labels",
        "Use aria-labelledby for complex labels",
        "Ensure labels are descriptive"
      ],
      "details": {
        "count": 1
      }
    },
    {
      "type": "MULTIPLE_H1",
      "severity": "low",
      "message": "♿ Page has 12 <h1> headings (should have 1)",
      "fix": [
        "Use only one <h1> per page",
        "Convert additional h1s to h2/h3",
        "Maintain proper heading hierarchy",
        "Use h1 for main content heading only"
      ],
      "details": {
        "noH1": false,
        "multipleH1": true,
        "total": 12
      }
    },
    {
      "type": "LONG_PAGE_TITLE",
      "severity": "low",
      "message": "📄 Page title too long (62 chars)",
      "fix": [
        "Keep title under 60 characters",
        "Most important info first",
        "Avoid keyword stuffing",
        "Include brand name at end",
        "Make title compelling for clicks"
      ],
      "details": {
        "length": 62,
        "title": "API Documentation - ODAVL Studio | Complete REST API Reference"
      }
    },
    {
      "type": "MISSING_STRUCTURED_DATA",
      "severity": "low",
      "message": "📊 Missing structured data (Schema.org)",
      "fix": [
        "Add JSON-LD structured data",
        "Use Schema.org vocabulary",
        "Implement appropriate types (Article, Product, etc.)",
        "Test with Google Rich Results Test",
        "Enable rich snippets in search results"
      ],
      "details": {}
    },
    {
      "type": "SMALL_TAP_TARGETS",
      "severity": "medium",
      "message": "👆 30 tap target(s) too small (< 48x48px)",
      "fix": [
        "Increase button/link size to minimum 48x48px",
        "Add padding to clickable elements",
        "Increase spacing between tap targets",
        "Follow Material Design guidelines",
        "Test on actual touch devices"
      ],
      "details": {
        "count": 30,
        "elements": [
          {
            "text": "Insight API",
            "tag": "a",
            "width": 105,
            "height": 41
          },
          {
            "text": "Autopilot API",
            "tag": "a",
            "width": 122,
            "height": 41
          },
          {
            "text": "Guardian API",
            "tag": "a",
            "width": 120,
            "height": 41
          },
          {
            "text": "Organizations",
            "tag": "a",
            "width": 121,
            "height": 41
          },
          {
            "text": "Authentication",
            "tag": "a",
            "width": 127,
            "height": 41
          },
          {
            "text": "https://docs.odavl.com",
            "tag": "a",
            "width": 139,
            "height": 16
          },
          {
            "text": "Authorize",
            "tag": "button",
            "width": 152,
            "height": 34
          },
          {
            "text": "insight",
            "tag": "a",
            "width": 79,
            "height": 28
          },
          {
            "text": "",
            "tag": "button",
            "width": 32,
            "height": 22
          },
          {
            "text": "autopilot",
            "tag": "a",
            "width": 101,
            "height": 28
          },
          {
            "text": "",
            "tag": "button",
            "width": 32,
            "height": 22
          },
          {
            "text": "guardian",
            "tag": "a",
            "width": 101,
            "height": 28
          },
          {
            "text": "",
            "tag": "button",
            "width": 32,
            "height": 22
          },
          {
            "text": "analytics",
            "tag": "a",
            "width": 103,
            "height": 28
          },
          {
            "text": "",
            "tag": "button",
            "width": 32,
            "height": 22
          },
          {
            "text": "organizations",
            "tag": "a",
            "width": 156,
            "height": 28
          },
          {
            "text": "",
            "tag": "button",
            "width": 32,
            "height": 22
          },
          {
            "text": "projects",
            "tag": "a",
            "width": 93,
            "height": 28
          },
          {
            "text": "",
            "tag": "button",
            "width": 32,
            "height": 22
          },
          {
            "text": "users",
            "tag": "a",
            "width": 64,
            "height": 28
          },
          {
            "text": "",
            "tag": "button",
            "width": 32,
            "height": 22
          },
          {
            "text": "Documentation",
            "tag": "a",
            "width": 99,
            "height": 41
          },
          {
            "text": "Tutorials",
            "tag": "a",
            "width": 57,
            "height": 41
          },
          {
            "text": "Code Examples",
            "tag": "a",
            "width": 101,
            "height": 41
          },
          {
            "text": "GitHub Issues",
            "tag": "a",
            "width": 91,
            "height": 41
          },
          {
            "text": "Discord Community",
            "tag": "a",
            "width": 131,
            "height": 41
          },
          {
            "text": "Email Support",
            "tag": "a",
            "width": 93,
            "height": 41
          },
          {
            "text": "Terms of Service",
            "tag": "a",
            "width": 109,
            "height": 41
          },
          {
            "text": "Privacy Policy",
            "tag": "a",
            "width": 94,
            "height": 41
          },
          {
            "text": "API Terms",
            "tag": "a",
            "width": 69,
            "height": 41
          }
        ]
      }
    }
  ],
  "metrics": {
    "totalIssues": 5,
    "critical": 0,
    "high": 1,
    "medium": 1,
    "low": 3
  }
}